qvpy/__init__.py
qvpy/constants.py
qvpy/dotdict.py
qvpy/qvpak.py
qvpy/mock/__init__.py
qvpy/mock/database.py
qvpy/mock/hardware.py
qvpy/mock/quickvision.py
qvpy/mock/software.py
qvpy/mock/video_tools.py
qvpy-0.0.3.dist-info/DESCRIPTION.rst
qvpy-0.0.3.dist-info/METADATA
qvpy-0.0.3.dist-info/RECORD
qvpy-0.0.3.dist-info/WHEEL
qvpy-0.0.3.dist-info/metadata.json
qvpy-0.0.3.dist-info/top_level.txt
tests/__init__.py
tests/test_dotdict.py
tests/test_mitutoyo.py
