Metadata-Version: 2.0
Name: qvpy
Version: 0.0.3
Summary: Mitutoyo QVPak COM client
Home-page: https://bitbucket.org/hirschbeutel/qvpy
Author: hirschbeutel
Author-email: hirschbeutel@gmail.com
License: MIT
Platform: UNKNOWN
